align_trim2/align_trim.py
align_trim2/readbedfile.py
align_trim2-1.0.0.dist-info/METADATA
align_trim2-1.0.0.dist-info/WHEEL
align_trim2-1.0.0.dist-info/entry_points.txt
align_trim2-1.0.0.dist-info/RECORD
