Metadata-Version: 2.1
Name: align-trim2
Version: 1.0.0
Summary: 
Author: ChrisKent
Author-email: chrisgkent@gmail.com
Requires-Python: >=3.10,<4.0
Classifier: Programming Language :: Python :: 3
Classifier: Programming Language :: Python :: 3.10
Classifier: Programming Language :: Python :: 3.11
Requires-Dist: pandas (>=2.2.1,<3.0.0)
Requires-Dist: pysam (>=0.22.0,<0.23.0)
